episuite/__init__.py
episuite/data.py
episuite/distributions.py
episuite/durations.py
episuite/icu.py
episuite/prevalence.py
episuite/mobility/__init__.py
episuite/mobility/facebook.py
episuite/mobility/google.py
episuite/sample_data/a.csv
episuite/sample_data/admission_sample.csv
tests/__init__.py
tests/test_data.py
tests/test_distributions.py
tests/test_durations.py
tests/test_icu.py
tests/test_main.py
tests/test_mobility.py
tests/test_prevalence.py
episuite-0.3.0.dist-info/LICENSE
episuite-0.3.0.dist-info/METADATA
episuite-0.3.0.dist-info/WHEEL
episuite-0.3.0.dist-info/top_level.txt
episuite-0.3.0.dist-info/RECORD
