Metadata-Version: 2.1
Name: episuite
Version: 0.3.0
Summary: A suite of tools for epidemiology in Python
Home-page: https://github.com/perone/episuite
Author: Christian S. Perone
Author-email: christian.perone@gmail.com
License: UNKNOWN
Project-URL: Bug Tracker, https://github.com/perone/episuite/issues
Platform: UNKNOWN
Classifier: Programming Language :: Python :: 3
Classifier: License :: OSI Approved :: MIT License
Classifier: Operating System :: OS Independent
Requires-Python: >=3.7
Requires-Dist: numpy (>=1.20.1)
Requires-Dist: matplotlib (>=3.3.4)
Requires-Dist: pandas (>=1.2.3)
Requires-Dist: numpyro (>=0.6.0)
Requires-Dist: arviz (>=0.11.2)
Requires-Dist: seaborn (>=0.11.1)
Requires-Dist: tqdm (>=4.59.0)
Requires-Dist: requests (>=2.25.1)
Requires-Dist: appdirs (>=1.4.4)
Requires-Dist: beautifulsoup4 (>=4.9.3)
Provides-Extra: dev
Requires-Dist: pytest (>=6.2.2) ; extra == 'dev'
Requires-Dist: mypy (>=0.812) ; extra == 'dev'
Requires-Dist: flake8 (>=3.8.4) ; extra == 'dev'
Requires-Dist: pytest-cov (>=2.11.1) ; extra == 'dev'
Requires-Dist: sphinx (>=3.5.2) ; extra == 'dev'
Requires-Dist: pydata-sphinx-theme (>=0.5.0) ; extra == 'dev'
Requires-Dist: sphinx-tabs (>=2.1.0) ; extra == 'dev'
Requires-Dist: nbsphinx (>=0.8.2) ; extra == 'dev'
Requires-Dist: ipykernel (>=5.5.0) ; extra == 'dev'
Requires-Dist: isort (>=5.7.0) ; extra == 'dev'
Requires-Dist: invoke (>=1.5.0) ; extra == 'dev'
Requires-Dist: pydocstyle (>=5.1.1) ; extra == 'dev'
Requires-Dist: twine (>=3.3.0) ; extra == 'dev'
Requires-Dist: sphinx-autobuild (>=2021.3.14) ; extra == 'dev'
Requires-Dist: ipywidgets (>=7.6.3) ; extra == 'dev'
Requires-Dist: sphinxcontrib-bibtex (>=2.2.0) ; extra == 'dev'
